blimpy/__init__.py
blimpy/bl_scrunch.py
blimpy/calcload.py
blimpy/dice.py
blimpy/dsamp.py
blimpy/fil2h5.py
blimpy/guppi.py
blimpy/h52fil.py
blimpy/h5diag.py
blimpy/match_fils.py
blimpy/peek.py
blimpy/rawhdr.py
blimpy/srcname.py
blimpy/stax.py
blimpy/stix.py
blimpy/utils.py
blimpy/waterfall.py
blimpy/calib_utils/__init__.py
blimpy/calib_utils/calib_plots.py
blimpy/calib_utils/explore_calibrators.py
blimpy/calib_utils/fluxcal.py
blimpy/calib_utils/stokescal.py
blimpy/ephemeris/__init__.py
blimpy/ephemeris/compute_lsrk.py
blimpy/ephemeris/compute_lst.py
blimpy/ephemeris/config.py
blimpy/ephemeris/observatory.py
blimpy/ephemeris/observatory_info.csv
blimpy/io/__init__.py
blimpy/io/base_reader.py
blimpy/io/fil_reader.py
blimpy/io/fil_writer.py
blimpy/io/file_wrapper.py
blimpy/io/hdf_reader.py
blimpy/io/hdf_writer.py
blimpy/io/sigproc.py
blimpy/plotting/__init__.py
blimpy/plotting/config.py
blimpy/plotting/plot_all.py
blimpy/plotting/plot_kurtosis.py
blimpy/plotting/plot_spectrum.py
blimpy/plotting/plot_spectrum_min_max.py
blimpy/plotting/plot_time_series.py
blimpy/plotting/plot_utils.py
blimpy/plotting/plot_waterfall.py
blimpy/signal_processing/__init__.py
blimpy/signal_processing/dedoppler.py
tests/__init__.py
tests/data.py
tests/download_data.sh
tests/run_tests.sh
tests/test_bl_scrunch.py
tests/test_calc_n_coarse_chan.py
tests/test_calcload.py
tests/test_compare_voyager.py
tests/test_dedoppler.py
tests/test_dice.py
tests/test_dsamp.py
tests/test_ephemeris.py
tests/test_fil2h5.py
tests/test_file_wrapper.py
tests/test_filterbank_voyager.py
tests/test_guppi.py
tests/test_h52fil.py
tests/test_h5diag.py
tests/test_h5py.py
tests/test_heavy.py
tests/test_match_fils.py
tests/test_observatory.py
tests/test_plotting.py
tests/test_setup.py
tests/test_sigproc.py
tests/test_stax.py
tests/test_stix.py
tests/test_unpack.py
tests/test_utils.py
tests/test_voyager_data_load.py
tests/test_waterfall.py
tests/test_waterfall2.py
tests/test_write_to_fil.py
blimpy-2.1.2.dist-info/LICENSE
blimpy-2.1.2.dist-info/METADATA
blimpy-2.1.2.dist-info/WHEEL
blimpy-2.1.2.dist-info/entry_points.txt
blimpy-2.1.2.dist-info/top_level.txt
blimpy-2.1.2.dist-info/RECORD
