Metadata-Version: 2.1
Name: blimpy
Version: 2.1.2
Summary: Python utilities for Breakthrough Listen SETI observations
Home-page: https://github.com/ucberkeleyseti/blimpy
Author: Danny Price, Emilio Enriquez, Yuhong Chen, Mark Siebert, and BL contributors
Author-email: dancpr@berkeley.edu
License: BSD
Platform: UNKNOWN
Classifier: Development Status :: 5 - Production/Stable
Classifier: Environment :: Console
Classifier: Natural Language :: English
Classifier: Operating System :: POSIX :: Linux
Classifier: Programming Language :: Python :: 3.7
Classifier: Intended Audience :: Science/Research
Classifier: License :: OSI Approved :: BSD License
Classifier: Topic :: Scientific/Engineering :: Astronomy
License-File: LICENSE
Requires-Dist: astropy
Requires-Dist: numpy (>=1.19)
Requires-Dist: six
Requires-Dist: setuptools
Requires-Dist: matplotlib
Requires-Dist: h5py
Requires-Dist: scipy
Requires-Dist: hdf5plugin
Requires-Dist: pandas
Requires-Dist: Pillow
Requires-Dist: psutil
Requires-Dist: pyparsing (==2.4.7)
